newsapi/__init__.py
python_newsapi-1.0.2.dist-info/DESCRIPTION.rst
python_newsapi-1.0.2.dist-info/METADATA
python_newsapi-1.0.2.dist-info/RECORD
python_newsapi-1.0.2.dist-info/WHEEL
python_newsapi-1.0.2.dist-info/metadata.json
python_newsapi-1.0.2.dist-info/top_level.txt
